typeform/__init__.py
typeform/client.py
typeform/constants.py
typeform/forms.py
typeform/responses.py
typeform/utils.py
typeform/test/__init__.py
typeform/test/fixtures.py
typeform/test/suite.py
typeform/test/test_client.py
typeform/test/test_forms.py
typeform/test/test_responses.py
typeform-1.1.0.dist-info/LICENSE
typeform-1.1.0.dist-info/METADATA
typeform-1.1.0.dist-info/WHEEL
typeform-1.1.0.dist-info/top_level.txt
typeform-1.1.0.dist-info/RECORD
