Metadata-Version: 2.1
Name: typeform
Version: 1.1.0
Summary: Python Client wrapper for Typeform API
Home-page: https://github.com/MichaelSolati/typeform-python-sdk
Author: Typeform
Author-email: michael.solati@typeform.com
License: MIT
Keywords: type,form,typeform,api
Platform: UNKNOWN
Classifier: Development Status :: 4 - Beta
Classifier: Intended Audience :: Developers
Classifier: License :: OSI Approved :: MIT License
Classifier: Operating System :: OS Independent
Classifier: Programming Language :: Python :: 3
Classifier: Programming Language :: Python :: 3.5
Classifier: Programming Language :: Python :: 3.6
Classifier: Programming Language :: Python :: 3.7
Classifier: Programming Language :: Python
Requires-Dist: requests
